flask_kvsession/__init__.py
Flask_KVSession_Ext-0.6.3.dev1.dist-info/LICENSE
Flask_KVSession_Ext-0.6.3.dev1.dist-info/METADATA
Flask_KVSession_Ext-0.6.3.dev1.dist-info/WHEEL
Flask_KVSession_Ext-0.6.3.dev1.dist-info/top_level.txt
Flask_KVSession_Ext-0.6.3.dev1.dist-info/RECORD
