Metadata-Version: 2.1
Name: Flask-KVSession-Ext
Version: 0.6.3.dev1
Summary: Transparent server-side session support for flask
Home-page: https://github.com/papadp/flask-kvsession
Author: UNKNOWN
Author-email: UNKNOWN
License: MIT
Platform: any
Classifier: Programming Language :: Python :: 2
Classifier: Programming Language :: Python :: 3
Requires-Dist: Flask (>=0.8)
Requires-Dist: simplekv (>=0.9.2)
Requires-Dist: werkzeug
Requires-Dist: itsdangerous (>=0.20)
Requires-Dist: six
